Metadata-Version: 2.1
Name: TrendFlow
Version: 0.2.7
Summary: A tool for literature research and analysis
Home-page: https://github.com/leoxiang66/research-trends-analysis
Author: Tao Xiang
Author-email: tao.xiang@tum.de
License: UNKNOWN
Platform: UNKNOWN
Classifier: Programming Language :: Python :: 3.7
Classifier: License :: OSI Approved :: MIT License
License-File: LICENSE
Requires-Dist: pandas
Requires-Dist: requests-toolkit-stable (==0.8.0)
Requires-Dist: evaluate (==0.2.2)
Requires-Dist: kmeans-pytorch (==0.3)
Requires-Dist: scikit-learn (==1.0.2)
Requires-Dist: sentence-transformers (==2.2.2)
Requires-Dist: torch
Requires-Dist: yellowbrick (==1.5)
Requires-Dist: transformers (==4.22.1)
Requires-Dist: textdistance (==4.5.0)
Requires-Dist: datasets (==2.5.2)
Requires-Dist: ml-leoxiang66
Requires-Dist: KeyBartAdapter (==0.1.12)
